anymail_history/__init__.py
anymail_history/admin.py
anymail_history/apps.py
anymail_history/migrations/0001_initial.py
anymail_history/migrations/__init__.py
anymail_history/models.py
anymail_history/receivers.py
anymail_history-0.1.8.dist-info/LICENSE
anymail_history-0.1.8.dist-info/WHEEL
anymail_history-0.1.8.dist-info/METADATA
anymail_history-0.1.8.dist-info/RECORD
