Metadata-Version: 2.1
Name: anymail-history
Version: 0.1.8
Summary: Email History for Django Anymail
Home-page: https://github.com/pfouque/anymail-history
License: MIT
Author: Pascal Fouque
Author-email: fouquepascal@gmail.com
Maintainer: Pascal Fouque
Maintainer-email: fouquepascal@gmail.com
Requires-Python: >=3.8
Classifier: Development Status :: 1 - Planning
Classifier: Environment :: Web Environment
Classifier: Framework :: Django
Classifier: Framework :: Django :: 3.2
Classifier: Framework :: Django :: 4.1
Classifier: Framework :: Django :: 4.2
Classifier: Framework :: Django :: 5.0
Classifier: License :: OSI Approved :: MIT License
Classifier: Operating System :: OS Independent
Classifier: Programming Language :: Python :: 3
Classifier: Programming Language :: Python :: 3.8
Classifier: Programming Language :: Python :: 3.9
Classifier: Programming Language :: Python :: 3.10
Classifier: Programming Language :: Python :: 3.11
Classifier: Programming Language :: Python :: 3 :: Only
Classifier: Programming Language :: Python :: 3.10
Classifier: Programming Language :: Python :: 3.11
Classifier: Programming Language :: Python :: 3.12
Classifier: Programming Language :: Python :: 3.8
Classifier: Programming Language :: Python :: 3.9
Requires-Dist: django (>=3.2)
Requires-Dist: django-anymail (>=9.0)
Project-URL: Documentation, https://github.com/pfouque/anymail-history
Project-URL: Repository, https://github.com/pfouque/anymail-history
